fintoolbox/__init__.py
fintoolbox/fintoolbox.py
fintoolbox/utils.py
fintoolbox-0.1.0.dist-info/AUTHORS.rst
fintoolbox-0.1.0.dist-info/LICENSE
fintoolbox-0.1.0.dist-info/METADATA
fintoolbox-0.1.0.dist-info/WHEEL
fintoolbox-0.1.0.dist-info/top_level.txt
fintoolbox-0.1.0.dist-info/RECORD
