Metadata-Version: 2.1
Name: fintoolbox
Version: 0.1.0
Summary: Fintoolbox contains all the tools need to construct and manage financial portfolios.
Home-page: https://github.com/rgno1/fintoolbox
Author: Rafael Girotto
Author-email: rafaelgirotto@gmail.com
License: MIT license
Keywords: fintoolbox
Platform: UNKNOWN
Classifier: Development Status :: 2 - Pre-Alpha
Classifier: Intended Audience :: Developers
Classifier: License :: OSI Approved :: MIT License
Classifier: Natural Language :: English
Classifier: Programming Language :: Python :: 3
Classifier: Programming Language :: Python :: 3.6
Classifier: Programming Language :: Python :: 3.7
Classifier: Programming Language :: Python :: 3.8
Requires-Python: >=3.6
License-File: LICENSE
License-File: AUTHORS.rst
